pytest_awaiting_fix/__init__.py
pytest_awaiting_fix/plugin.py
pytest_awaiting_fix-1.2.dist-info/licenses/LICENSE
pytest_awaiting_fix-1.2.dist-info/METADATA
pytest_awaiting_fix-1.2.dist-info/WHEEL
pytest_awaiting_fix-1.2.dist-info/entry_points.txt
pytest_awaiting_fix-1.2.dist-info/top_level.txt
pytest_awaiting_fix-1.2.dist-info/RECORD
