Metadata-Version: 2.4
Name: pytest-awaiting-fix
Version: 1.2
Summary: A simple plugin to use with pytest for traceability across Jira and disabled automated tests
Author-email: Kie Baker <kiebakerr@proton.me>
Maintainer-email: Kie Baker <kiebakerr@proton.me>
License: 
Project-URL: Repository, https://github.com/kiebak3r/pytest-awaiting-fix
Classifier: Framework :: Pytest
Classifier: Development Status :: 4 - Beta
Classifier: Intended Audience :: Developers
Classifier: Topic :: Software Development :: Testing
Classifier: Operating System :: OS Independent
Classifier: Programming Language :: Python
Classifier: Programming Language :: Python :: 3.8
Classifier: Programming Language :: Python :: 3.9
Classifier: Programming Language :: Python :: 3.10
Classifier: Programming Language :: Python :: 3.11
Classifier: Programming Language :: Python :: 3.12
Classifier: Programming Language :: Python :: 3 :: Only
Classifier: Programming Language :: Python :: Implementation :: CPython
Classifier: Programming Language :: Python :: Implementation :: PyPy
Classifier: License :: OSI Approved :: MIT License
Requires-Python: >=3.8
License-File: LICENSE
Requires-Dist: pytest>=6.2.0
Requires-Dist: jira>=3.8.0
Dynamic: license-file
